{"digest":"2cd7f09186fe2d85d337f65409373207ae0887fc","css":"atom-text-editor[data-grammar=\"source python\"] .autocomplete-suggestion-list.select-list.popover-list .suggestion-description-content,\n:host .autocomplete-suggestion-list.select-list.popover-list .suggestion-description-content {\n  white-space: pre-wrap;\n}\nautocomplete-python-suggestion {\n  width: auto;\n  display: inline-block;\n  min-width: 200px;\n  max-width: 800px;\n  color: #d4d7d6;\n  padding: 5px 0;\n  padding-left: 0.6em;\n  padding-right: 0.6em;\n  min-height: 2em;\n  line-height: 1.3;\n  background: #050607;\n  border-radius: 0 0 0 0;\n  max-height: 312px;\n  overflow-y: scroll;\n  white-space: pre-wrap;\n  font-family: 'BlinkMacSystemFont', 'Lucida Grande', 'Segoe UI', Ubuntu, Cantarell, sans-serif;\n}\n","imports":[{"path":"static/variables/ui-variables.less","digest":"c6d5219b02cf3129dbc56c526ad6541ba4e237e6"},{"path":"static/variables/syntax-variables.less","digest":"812c1b7883a023f768773d14294653adcdb932d7"},{"path":"/home/epse/EpConfFiles/atom/.atom/packages/seti-ui/styles/ui-variables.less","digest":"e790c8628b5177d0bebec87b726f55dd3ad58e7f"},{"path":"/home/epse/EpConfFiles/atom/.atom/packages/seti-ui/styles/default-theme.less","digest":"b9f29c7eaf933fbae9455b407945e01dee4cc440"},{"path":"/home/epse/EpConfFiles/atom/.atom/packages/seti-ui/styles/user-theme.less","digest":"91ee297551d60a5909f8a475cbdc30ca24c9f5f4"}],"version":1}